RobotGrpc/__init__.py
RobotGrpc-1.2.1.dist-info/METADATA
RobotGrpc-1.2.1.dist-info/WHEEL
RobotGrpc-1.2.1.dist-info/top_level.txt
RobotGrpc-1.2.1.dist-info/RECORD
